configwidgets/__init__.py
configwidgets/buttons.py
configwidgets/containers.py
configwidgets/datetime.py
configwidgets/error.py
configwidgets/numbers.py
configwidgets/path.py
configwidgets/settings.py
configwidgets/text.py
configwidgets/static/pathselect.ui
configwidgets-1.4.1.dist-info/LICENSE
configwidgets-1.4.1.dist-info/METADATA
configwidgets-1.4.1.dist-info/WHEEL
configwidgets-1.4.1.dist-info/top_level.txt
configwidgets-1.4.1.dist-info/RECORD
