Metadata-Version: 2.1
Name: configwidgets
Version: 1.4.1
Summary: Subclassing PyQt5.QtWidgets to syncronize state in QSettings object.
Author-email: Kolja Wagner <k.wagner@meteo.uni-hannover.de>
Project-URL: Documentation, https://configwidgets.readthedocs.io/en/latest/
Project-URL: Repository, https://github.com/kolja-wagner/configwidgets
Requires-Python: >=3.7
License-File: LICENSE
Requires-Dist: PyQt5 >=5.15
